simpledataquality/__init__.py
simpledataquality/publish.py
simpledataquality/validator.py
simpledataquality-1.0.8.dist-info/LICENSE
simpledataquality-1.0.8.dist-info/METADATA
simpledataquality-1.0.8.dist-info/WHEEL
simpledataquality-1.0.8.dist-info/top_level.txt
simpledataquality-1.0.8.dist-info/RECORD
