Metadata-Version: 2.1
Name: simpledataquality
Version: 1.0.8
Summary: A package implement a basic data quelity check
Home-page: https://github.com/amedinag32/simpledataquality
Author: Alan Medina
Author-email: amedina.escom@hotmail.com
License: UNKNOWN
Platform: UNKNOWN
Classifier: Programming Language :: Python :: 3
Classifier: License :: OSI Approved :: MIT License
Classifier: Operating System :: OS Independent
Requires-Python: >=3.8
Requires-Dist: SQLAlchemy (==2.0.36)
Requires-Dist: certifi (==2024.12.14)
Requires-Dist: charset-normalizer (==3.4.0)
Requires-Dist: greenlet (==3.1.1)
Requires-Dist: idna (==3.10)
Requires-Dist: mssqldbfacade (==1.0.8)
Requires-Dist: numpy (==1.24.4)
Requires-Dist: pandas (==2.0.3)
Requires-Dist: pandasql (==0.7.3)
Requires-Dist: pymssql (==2.2.7)
Requires-Dist: python-dateutil (==2.9.0.post0)
Requires-Dist: pytz (==2024.2)
Requires-Dist: requests (==2.32.3)
Requires-Dist: six (==1.17.0)
Requires-Dist: typing-extensions (==4.12.2)
Requires-Dist: tzdata (==2024.2)
Requires-Dist: urllib3 (==2.2.3)
